aaaaaa/__init__.py
aaaaaa-6.6.6.dist-info/LICENSE.txt
aaaaaa-6.6.6.dist-info/METADATA
aaaaaa-6.6.6.dist-info/WHEEL
aaaaaa-6.6.6.dist-info/top_level.txt
aaaaaa-6.6.6.dist-info/RECORD
